{
  "shelving_record": {
    "_id": {
      "$oid": "64f11b8f497c3069472b345c"
    },
    "identifier": "8krg",
    "target": "#",
    "class": "inventory",
    "allocated": true,
    "permalink": "https://joeeasterly.github.io/go/8krg",
    "label": "shelf 35",
    "last_updated": {
      "$date": "2023-12-24T20:44:54.472Z"
    },
    "notion_id": "261",
    "shcn": "35",
    "shelf": "35",
    "type": "storage"
  },
  "shelf_contents": [
    {
      "_id": {
        "$oid": "64f11b8f497c3069472b3e04"
      },
      "identifier": "8p5r",
      "target": "#",
      "class": "inventory",
      "allocated": true,
      "permalink": "https://joeeasterly.github.io/go/8p5r",
      "staged": "2024-01-07 13:56:33",
      "bay": "350",
      "label": "DeoxIt Fader F5 5oz Electronic Cleaner",
      "last_updated": {
        "$date": "2024-02-08T19:45:19.743Z"
      },
      "notion_id": "1447",
      "shcn": "350",
      "shelf": "35",
      "type": "item"
    },
    {
      "_id": {
        "$oid": "64f11b90497c3069472b4944"
      },
      "identifier": "8ryr",
      "target": "#",
      "class": "inventory",
      "allocated": true,
      "permalink": "https://joeeasterly.github.io/go/8ryr",
      "staged": "2024-01-19 11:39:27",
      "bay": "350",
      "expires": "2029-12-31 00:00:00",
      "label": "CRC QD 11oz Electronic Cleaner",
      "last_updated": {
        "$date": "2024-02-08T19:47:33.235Z"
      },
      "notion_id": "1449",
      "percentage": "100",
      "quantity": "1",
      "shcn": "350",
      "shelf": "35",
      "type": "consumable",
      "upc": "078254051031"
    },
    {
      "_id": {
        "$oid": "64f11b97497c3069472c7fcc"
      },
      "identifier": "b6kz",
      "target": "#",
      "class": "inventory",
      "allocated": true,
      "permalink": "https://joeeasterly.github.io/go/b6kz",
      "staged": "2024-01-07 13:56:33",
      "bay": "350",
      "expires": "2029-12-31 00:00:00",
      "label": "Max Pro Electronics Lubricant 11oz",
      "last_updated": {
        "$date": "2024-02-08T19:48:33.802Z"
      },
      "notion_id": "1450",
      "percentage": "100",
      "quantity": "1",
      "shcn": "350",
      "shelf": "35",
      "type": "consumable",
      "upc": "752080004125"
    },
    {
      "_id": {
        "$oid": "64f11b9c497c3069472d9c58"
      },
      "identifier": "ddrc",
      "target": "#",
      "class": "inventory",
      "allocated": true,
      "permalink": "https://joeeasterly.github.io/go/ddrc",
      "staged": "2024-01-19 11:39:27",
      "bay": "350",
      "label": "DeoxIt D5 5oz Electronic Cleaner",
      "last_updated": {
        "$date": "2024-02-08T19:46:04.899Z"
      },
      "notion_id": "1448",
      "shcn": "350",
      "shelf": "35",
      "type": "item"
    },
    {
      "_id": {
        "$oid": "64f11bb1497c306947317c5d"
      },
      "identifier": "n5rh",
      "target": "#",
      "class": "inventory",
      "allocated": true,
      "permalink": "https://joeeasterly.github.io/go/n5rh",
      "bay": "350",
      "label": "bay 350",
      "last_updated": {
        "$date": "2024-01-04T15:43:57.761Z"
      },
      "notion_id": "887",
      "shcn": "350",
      "shelf": "35",
      "type": "storage"
    }
  ]
}