{
  "shelving_record": {
    "_id": {
      "$oid": "64f11b9f497c3069472e29c2"
    },
    "identifier": "eh3p",
    "target": "#",
    "class": "inventory",
    "allocated": true,
    "permalink": "https://joeeasterly.github.io/go/eh3p",
    "label": "Primary Workstation",
    "last_updated": {
      "$date": "2024-01-26T20:18:27.683Z"
    },
    "notion_id": "369",
    "shcn": "44",
    "shelf": "44",
    "type": "storage"
  },
  "shelf_contents": [
    {
      "_id": {
        "$oid": "64f11b9e497c3069472dfc64"
      },
      "identifier": "e5rr",
      "target": "#",
      "class": "inventory",
      "allocated": true,
      "permalink": "https://joeeasterly.github.io/go/e5rr",
      "bay": "442",
      "label": "keyboard drawer",
      "last_updated": {
        "$date": "2024-01-04T17:04:04.276Z"
      },
      "notion_id": "899",
      "shcn": "442",
      "shelf": "44",
      "type": "storage"
    },
    {
      "_id": {
        "$oid": "64f11bae497c30694730f294"
      },
      "identifier": "m3a8",
      "target": "#",
      "class": "inventory",
      "allocated": true,
      "permalink": "https://joeeasterly.github.io/go/m3a8",
      "bay": "441",
      "label": "upper shelf",
      "last_updated": {
        "$date": "2024-01-04T17:03:32.924Z"
      },
      "notion_id": "898",
      "shcn": "441",
      "shelf": "44",
      "type": "storage"
    },
    {
      "_id": {
        "$oid": "64f11bb6497c306947327912"
      },
      "identifier": "q4x6",
      "target": "#",
      "class": "inventory",
      "allocated": true,
      "permalink": "https://joeeasterly.github.io/go/q4x6",
      "bay": "440",
      "label": "bay 440",
      "last_updated": {
        "$date": "2024-01-04T17:02:56.636Z"
      },
      "notion_id": "897",
      "shcn": "440",
      "shelf": "44",
      "type": "storage"
    },
    {
      "_id": {
        "$oid": "64f11bd0497c3069473757d7"
      },
      "identifier": "zvmb",
      "target": "#",
      "class": "inventory",
      "allocated": true,
      "permalink": "https://joeeasterly.github.io/go/zvmb",
      "bay": "443",
      "label": "lower shelf",
      "last_updated": {
        "$date": "2024-01-04T17:05:54.095Z"
      },
      "notion_id": "900",
      "shcn": "443",
      "shelf": "44",
      "type": "storage"
    }
  ]
}