{
  "shelving_record": {
    "_id": {
      "$oid": "64f11bc8497c30694735d5d0"
    },
    "identifier": "wv44",
    "target": "#",
    "class": "inventory",
    "allocated": true,
    "permalink": "https://joeeasterly.github.io/go/wv44",
    "bay": "411",
    "container": "4110",
    "label": "slot 4110D",
    "last_updated": {
      "$date": "2023-12-24T16:57:25.414Z"
    },
    "notion_id": "680",
    "shcn": "4110D",
    "shelf": "41",
    "slot": "4110D",
    "type": "storage"
  },
  "shelf_contents": [
    {
      "_id": {
        "$oid": "64f11b95497c3069472c38d5"
      },
      "identifier": "amv9",
      "target": "#",
      "class": "inventory",
      "allocated": true,
      "permalink": "https://joeeasterly.github.io/go/amv9",
      "label": "1 1/4in #8 plaster screws",
      "last_updated": {
        "$date": "2023-10-18T14:35:01.518Z"
      },
      "notion_id": "398",
      "shelf": "41",
      "bay": "411",
      "container": "4110",
      "shcn": "4110D",
      "slot": "4110D"
    },
    {
      "_id": {
        "$oid": "64f11b9c497c3069472d7b97"
      },
      "identifier": "d5jb",
      "target": "#",
      "class": "inventory",
      "allocated": true,
      "permalink": "https://joeeasterly.github.io/go/d5jb",
      "label": "1in #6 drywall screws",
      "last_updated": {
        "$date": "2023-10-18T14:34:47.592Z"
      },
      "notion_id": "397",
      "shelf": "41",
      "bay": "411",
      "container": "4110",
      "shcn": "4110D",
      "slot": "4110D"
    },
    {
      "_id": {
        "$oid": "64f11bab497c306947306361"
      },
      "identifier": "jygn",
      "target": "#",
      "class": "inventory",
      "allocated": true,
      "permalink": "https://joeeasterly.github.io/go/jygn",
      "label": "1 1/4in #8 plaster anchors",
      "last_updated": {
        "$date": "2023-10-18T14:34:40.017Z"
      },
      "notion_id": "402",
      "shelf": "41",
      "bay": "411",
      "container": "4110",
      "shcn": "4110D",
      "slot": "4110D"
    },
    {
      "_id": {
        "$oid": "64f11bc8497c30694735d5d0"
      },
      "identifier": "wv44",
      "target": "#",
      "class": "inventory",
      "allocated": true,
      "permalink": "https://joeeasterly.github.io/go/wv44",
      "bay": "411",
      "container": "4110",
      "label": "slot 4110D",
      "last_updated": {
        "$date": "2023-12-24T16:57:25.414Z"
      },
      "notion_id": "680",
      "shcn": "4110D",
      "shelf": "41",
      "slot": "4110D",
      "type": "storage"
    }
  ]
}